niicat/__init__.py
niicat/cli.py
niicat/plotter.py
niicat/resources/__init__.py
niicat/resources/imgcat.sh
niicat/resources/niipre_to_buffer.py
niicat-0.5.0.dist-info/LICENSE
niicat-0.5.0.dist-info/METADATA
niicat-0.5.0.dist-info/WHEEL
niicat-0.5.0.dist-info/entry_points.txt
niicat-0.5.0.dist-info/top_level.txt
niicat-0.5.0.dist-info/RECORD
