Metadata-Version: 2.1
Name: niicat
Version: 0.5.0
Summary: Preview nifti images on the terminal
Home-page: https://github.com/MIC-DKFZ/niicat/
Author: Jakob Wasserthal
Author-email: j.wasserthal@dkfz.de
License: GPL v2
Classifier: Intended Audience :: Science/Research
Classifier: Programming Language :: Python
Classifier: Topic :: Scientific/Engineering :: Bio-Informatics
Classifier: Operating System :: Unix
Classifier: Operating System :: MacOS
Requires-Python: >=3.7
License-File: LICENSE
Requires-Dist: nibabel>=2.3.0
Requires-Dist: matplotlib
Requires-Dist: numpy
Requires-Dist: importlib-metadata; python_version < "3.8"
Provides-Extra: libsixel
Requires-Dist: libsixel-python; extra == "libsixel"
